pyben/__init__.py
pyben/api.py
pyben/bencode.py
pyben/classes.py
pyben/exceptions.py
pyben/version.py
pyben-0.3.2.dist-info/LICENSE
pyben-0.3.2.dist-info/METADATA
pyben-0.3.2.dist-info/WHEEL
pyben-0.3.2.dist-info/top_level.txt
pyben-0.3.2.dist-info/RECORD
