Metadata-Version: 2.1
Name: pyben
Version: 0.3.2
Summary: Small library for encoding/decoding bencode data. Pyben Enables fast and easy encoding and decoding of bencoded data.
Home-page: https://github.com/alexpdev/pyben
Author: alexpdev
Author-email: alexpdev@protonmail.com
License: Apache 2.0
Project-URL: Source Code, https://github.com/alexpdev/pyben
Keywords: library,bencode
Platform: any
Classifier: Development Status :: 3 - Alpha
Classifier: Operating System :: OS Independent
Classifier: Programming Language :: Python :: 3.6
Classifier: Programming Language :: Python :: 3.7
Classifier: Programming Language :: Python :: 3.8
Classifier: Programming Language :: Python :: 3.9
Classifier: Topic :: Software Development :: Libraries :: Python Modules
Classifier: License :: OSI Approved :: GNU Lesser General Public License v3 (LGPLv3)
License-File: LICENSE
